pytenno/__asynciofix.py
pytenno/__init__.py
pytenno/__main__.py
pytenno/_backends/auction_entries.py
pytenno/_backends/auctions.py
pytenno/_backends/auth.py
pytenno/_backends/core.py
pytenno/_backends/items.py
pytenno/_backends/liches.py
pytenno/_backends/misc.py
pytenno/_backends/profile.py
pytenno/_backends/rivens.py
pytenno/client.py
pytenno/constants.py
pytenno/errors.py
pytenno/interface/auction_entries.py
pytenno/interface/auctions.py
pytenno/interface/auth.py
pytenno/interface/items.py
pytenno/interface/liches.py
pytenno/interface/misc.py
pytenno/interface/profile.py
pytenno/interface/rivens.py
pytenno/models/__init__.py
pytenno/models/auctions.py
pytenno/models/bids.py
pytenno/models/droptable.py
pytenno/models/enums.py
pytenno/models/items.py
pytenno/models/liches.py
pytenno/models/locations.py
pytenno/models/missions.py
pytenno/models/orders.py
pytenno/models/rivens.py
pytenno/models/users.py
pytenno/utils.py
pytenno-1.3.3.dist-info/LICENSE
pytenno-1.3.3.dist-info/METADATA
pytenno-1.3.3.dist-info/WHEEL
pytenno-1.3.3.dist-info/RECORD
