Metadata-Version: 2.1
Name: pytenno
Version: 1.3.3
Summary: A asynchronous Python library for interacting with the warframe.market API
Home-page: https://github.com/ShadowMagic896/pytenno
License: MIT
Keywords: warframe,market,api,asyncio,aiohttp,wrapper
Author: Ryan Peckham
Author-email: 86629697+ShadowMagic896@users.noreply.github.com
Maintainer: Ryan Peckham
Maintainer-email: 86629697+ShadowMagic896@users.noreply.github.com
Requires-Python: >=3.10,<4.0
Classifier: License :: OSI Approved :: MIT License
Classifier: Programming Language :: Python
Classifier: Programming Language :: Python :: 3
Classifier: Programming Language :: Python :: 3.10
Classifier: Programming Language :: Python :: 3.11
Classifier: Programming Language :: Python :: 3.12
Requires-Dist: aiohttp (>=3.8.1,<4.0.0)
Project-URL: Bug Tracker, https://github.com/ShadowMagic896/pytenno/issues
Project-URL: Documentation, https://pytenno.readthedocs.io
Project-URL: Repository, https://github.com/ShadowMagic896/pytenno
